{
  "Sold as": "MDMA / Ecstasy",
  "Expected to be": "Not Specified",
  "Lab Comments": "Not Available",
  "Warning": "The European drug checking group that analyzed this tablet issued a warning for it, stipulating that 1.3 milligrams MDMA per kilogram of body weight in women and 1.5 milligrams of MDMA per kilogram of body weight in men should not be exceeded. Tablet has a break line on reverse side.",
  "Image": "13978.jpg",
  "table data left": {
    "ID": "13978",
    "Name": "The Punisher",
    "Other Names": "",
    "HPLC:The HPLC Lab Test": "",
    "list_4": [
      "MDMA\n\n\n: 270.90 mg\n\nMDMA aka Ecstasy, E, X"
    ]
  },
  "table data right": {
    "Test Date": "Aug 13, 2022",
    "Pub. Date": "Sep 02, 2022",
    "Src Location": "Zurich, \nSwitzerland",
    "Submitter Loc": "Zurich, --Switzerland",
    "Color": "Teal Blue",
    "Size": "514.2 mg, 14.10 mm x 10.80 mm x 5.4 mm",
    "Data Source": "SaferParty.ch",
    "Tested by": "Mobile Unit",
    "Lab's ID": "SP:202209-21"
  }
}