{
  "Sold as": "Fioricet",
  "Expected to be": "Butalbital / Acetaminophen / Caffeine",
  "Lab Comments": "Not Available",
  "Warning": "Please do not submit multiple samples to DrugsData with a single submission form without prior approval.",
  "Image": "15905.jpg",
  "table data left": {
    "ID": "15905",
    "Name": "LCI  1695",
    "Other Names": "",
    "UniqueCode:Unique Lookup Code is an alphanumeric string created by the submitter and included with the sample so anonymously submitted samples can be positively identified as the submitter's sample.": "11494",
    "Marquis:The Marquis Test is a reagent field test conducted by placing a drop of reagent liquid onto a small sample of the material being tested. The chemicals in the reagent react differently with different chemicals, turning a variety of colors based on the what is in the material being tested.": "No Reaction",
    "Liebermann": "Purple - Brown",
    "Froehde": "Blue",
    "GC/MS:The GC/MS Lab Test": "",
    "list_8": [
      "Acetaminophen\n\n\n: 3",
      "Caffeine\n\n\n: 2",
      "Butalbital\n\n\n: 1 \n\nButalbital aka Fioricet"
    ]
  },
  "table data right": {
    "Test Date": "Apr 11, 2023",
    "Pub. Date": "Apr 11, 2023",
    "Src Location": "Jacksonville, FL",
    "Submitter Loc": "St. Johns, FLUnited States",
    "Color": "Blue",
    "Size": "368 mg",
    "Data Source": "DrugsData",
    "Tested by": "DDL",
    "Lab's ID": "23030189"
  }
}