{
  "Sold as": "MDMA / Ecstasy",
  "Expected to be": "Not Specified",
  "Lab Comments": "Not Available",
  "Warning": "checkit issued a 'high dose' caution because this tablet contains more than 120mg of MDMA. Tablet scored on reverse side.",
  "Image": "5789.jpg",
  "table data left": {
    "ID": "5789",
    "Name": "Punisher",
    "Other Names": "",
    "HPLC:The HPLC Lab Test": "",
    "list_4": [
      "MDMA\n\n\n: 291 mg\n\nMDMA aka Ecstasy, E, X"
    ]
  },
  "table data right": {
    "Test Date": "Nov 09, 2017",
    "Pub. Date": "Nov 09, 2017",
    "Src Location": "Vienna, \nAustria",
    "Submitter Loc": "Vienna, --Austria",
    "Color": "Blue",
    "Size": "13.70 x 5.30",
    "Data Source": "CheckIt!",
    "Tested by": "CheckIt! Lab",
    "Lab's ID": "CH:201711-8"
  }
}