{
  "Sold as": "ecs",
  "Expected to be": "Not Specified",
  "Lab Comments": "Not Available",
  "Warning": "SaferParty issued an 'extreme high dose' warning because this tablet contains more than 200mg of MDMA. Tablet has a break line and the word 'THUNDERDOME' on reverse side.",
  "Image": "6521.jpg",
  "table data left": {
    "ID": "6521",
    "Name": "Thunderdome",
    "Other Names": "",
    "HPLC:The HPLC Lab Test": "",
    "list_4": [
      "MDMA\n\n\n: 232 mg\n\nMDMA aka Ecstasy, E, X"
    ]
  },
  "table data right": {
    "Test Date": "Aug 11, 2018",
    "Pub. Date": "Aug 24, 2018",
    "Src Location": "Zurich, \nSwitzerland",
    "Submitter Loc": "Zurich, --Switzerland",
    "Color": "Tan",
    "Size": "493.5 mg, 11.10 mm x 12.10 mm x 5.2 mm",
    "Data Source": "SaferParty.ch",
    "Tested by": "Mobile Unit",
    "Lab's ID": "SP:201808-25"
  }
}