{
  "Sold as": "Not Specified",
  "Expected to be": "Not Specified",
  "Lab Comments": "Not Available",
  "Warning": "''Had a blast''",
  "Image": "14684.jpg",
  "table data left": {
    "ID": "14684",
    "Name": "Tan Residue",
    "Other Names": "",
    "UniqueCode:Unique Lookup Code is an alphanumeric string created by the submitter and included with the sample so anonymously submitted samples can be positively identified as the submitter's sample.": "AC2022B1159",
    "Fentanyl Test Strip (FTS)": "Positive",
    "GC/MS:The GC/MS Lab Test": "",
    "list_6": [
      "Cocaine\n\n\n: 120 \n\nCocaine aka Crack, Coca",
      "Benzoylecgonine\n\n\n: 60",
      "Benzoic acid\n\n\n: 10",
      "Methylecgonidine\n\n\n: 10 \n\nMethylecgonidine aka Anhydroecgonine methyl ester; Methyl Ecgonidine; AEME",
      "Tropacocaine\n\n\n: 2 \n\nTropacocaine aka tropacaine, benzoylpseudotropine, pseudotropine benzoate",
      "Fentanyl\n\n\n: 1"
    ]
  },
  "table data right": {
    "Test Date": "Nov 03, 2022",
    "Pub. Date": "Nov 03, 2022",
    "Src Location": "Gloucester, MA",
    "Submitter Loc": "Gloucester, MAUnited States",
    "Color": "Tan",
    "Size": "1 mg",
    "Data Source": "DrugsData",
    "Tested by": "DDL",
    "Lab's ID": "22100156"
  }
}