{
  "Sold as": "Ecstasy / MDMA",
  "Expected to be": "Not Specified",
  "Lab Comments": "Not Available",
  "Warning": "SaferParty issued an 'extreme high dose' warning because this tablet contains more than 200mg of MDMA. No break line!",
  "Image": "6529.jpg",
  "table data left": {
    "ID": "6529",
    "Name": "Formel 1",
    "Other Names": "F-1; Formula 1; MAX",
    "HPLC:The HPLC Lab Test": "",
    "list_4": [
      "MDMA\n\n\n: 201.40 mg\n\nMDMA aka Ecstasy, E, X"
    ]
  },
  "table data right": {
    "Test Date": "Aug 21, 2018",
    "Pub. Date": "Aug 24, 2018",
    "Src Location": "Zurich, \nSwitzerland",
    "Submitter Loc": "Zurich, --Switzerland",
    "Color": "Green",
    "Size": "551 mg, 9.60 mm x 9.10 mm x 5.4 mm",
    "Data Source": "SaferParty.ch",
    "Tested by": "DIZ",
    "Lab's ID": "SP:201808-33"
  }
}