{
  "Sold as": "Cannabis",
  "Expected to be": "Not Specified",
  "Lab Comments": "Not Available",
  "Warning": "Not Available",
  "Image": "8669.jpg",
  "table data left": {
    "ID": "8669",
    "Name": "Adulterated Cannabis",
    "Other Names": "",
    "HPLC:The HPLC Lab Test": "",
    "list_4": [
      "5F-MDMB-PICA\n\n\n  \n\n5F-MDMB-PICA aka MDMB-2201; 5F-MDMB-2201",
      "CBD\n\n\n  \n\nCBD aka Cannabidiol",
      "MDMB-4en-PINACA\n\n\n  \n\nMDMB-4en-PINACA aka 5-CL-ADB-A; 5CI-ADB-A",
      "THJ-018\n\n\n  \n\nTHJ-018 aka 1-naphthalenyl(1-pentyl-1H-indazol-3-yl)-methanone;  JWH-018 indazole analog",
      "THC\n\n\n: trace \n\nTHC aka delta-9-THC"
    ]
  },
  "table data right": {
    "Test Date": "Jun 26, 2020",
    "Pub. Date": "Jul 10, 2020",
    "Src Location": "Zurich, \nSwitzerland",
    "Submitter Loc": "Zurich, --Switzerland",
    "Color": "Green / Brown",
    "Size": "-",
    "Data Source": "SaferParty.ch",
    "Tested by": "DIZ",
    "Lab's ID": "SP:202007-3"
  }
}